airfold_common/__init__.py
airfold_common/_pydantic.py
airfold_common/clickhouse.py
airfold_common/config.py
airfold_common/data.py
airfold_common/error.py
airfold_common/id.py
airfold_common/models.py
airfold_common/plan.py
airfold_common/project.py
airfold_common/provider.py
airfold_common/py.typed
airfold_common/schema.py
airfold_common/singleton.py
airfold_common/type.py
airfold_common/utils.py
airfold_common-0.14.3.dist-info/METADATA
airfold_common-0.14.3.dist-info/WHEEL
airfold_common-0.14.3.dist-info/top_level.txt
airfold_common-0.14.3.dist-info/RECORD
