Metadata-Version: 2.4
Name: airfold-common
Version: 0.14.3
Summary: Airfold Common
Author-email: Constantine Peresypkin <pconstantine@gmail.com>, Oleksandr Bazna <oleksandr.bazna@gmail.com>
Classifier: Development Status :: 3 - Alpha
Classifier: Programming Language :: Python :: 3.10
Classifier: Programming Language :: Python :: 3.11
Classifier: License :: OSI Approved :: Apache Software License
Classifier: Operating System :: OS Independent
Requires-Python: <4,>=3.10
Requires-Dist: pydantic<=3.0
Requires-Dist: pyyaml!=5.4.0,!=5.4.1,!=6.0.0
Requires-Dist: typer>=0.9.0
Requires-Dist: rich
Requires-Dist: sqlglot>=25.21.0
Requires-Dist: aiohttp
Requires-Dist: requests
Requires-Dist: python-dateutil
Provides-Extra: test
Requires-Dist: build; extra == "test"
Requires-Dist: isort; extra == "test"
Requires-Dist: black~=23.3; extra == "test"
Requires-Dist: mypy; extra == "test"
Requires-Dist: pytest; extra == "test"
Requires-Dist: pytest-dotenv; extra == "test"
Requires-Dist: retry; extra == "test"
Requires-Dist: types-pyyaml; extra == "test"
Requires-Dist: types-retry; extra == "test"
Requires-Dist: types-requests; extra == "test"
Requires-Dist: types-python-dateutil; extra == "test"
Requires-Dist: deepdiff; extra == "test"
